{
  "id": "troubleshooting-guide",
  "title": "故障排查",
  "description": "TODO",
  "source": "@site/i18n/zh/docusaurus-plugin-content-docs/version-2.5.2/troubleshooting-guide.md",
  "sourceDirName": ".",
  "slug": "/troubleshooting-guide",
  "permalink": "/zh/docs/2.5.2/troubleshooting-guide",
  "draft": false,
  "unlisted": false,
  "editUrl": "https://github.com/microdao-bio/website-microdao-bio/i18n/zh/docusaurus-plugin-content-docs/version-2.5.2/troubleshooting-guide.md",
  "tags": [],
  "version": "2.5.2",
  "frontMatter": {
    "title": "故障排查"
  }
}